AztClient/__init__.py
AztClient/api/__init__.py
AztClient/api/his_quote_api.py
AztClient/api/his_quote_spi.py
AztClient/api/quote_api.py
AztClient/api/quote_spi.py
AztClient/api/trade_api.py
AztClient/api/trade_spi.py
AztClient/protocols/EnumProto.py
AztClient/protocols/EnumType_pb2.py
AztClient/protocols/EnumType_pb2.pyi
AztClient/protocols/His_Quote_EnumType_pb2.py
AztClient/protocols/His_Quote_EnumType_pb2.pyi
AztClient/protocols/His_Quote_Message_pb2.py
AztClient/protocols/His_Quote_Message_pb2.pyi
AztClient/protocols/MsgProto.py
AztClient/protocols/MsgType_pb2.py
AztClient/protocols/MsgType_pb2.pyi
AztClient/protocols/Quote_Message_pb2.py
AztClient/protocols/Quote_Message_pb2.pyi
AztClient/protocols/Trade_Message_pb2.py
AztClient/protocols/Trade_Message_pb2.pyi
AztClient/protocols/UnitedMessage_pb2.py
AztClient/protocols/UnitedMessage_pb2.pyi
AztClient/protocols/__init__.py
AztClient/src/__init__.py
AztClient/src/his_quote_api_base.py
AztClient/src/quote_api_base.py
AztClient/src/trade_api_base.py
AztClient/structs/__init__.py
AztClient/structs/his_quote_api.py
AztClient/structs/his_quote_spi.py
AztClient/structs/quote_api.py
AztClient/structs/quote_spi.py
AztClient/structs/trade_api.py
AztClient/structs/trade_spi.py
AztClient/structs/py2pb/__init__.py
AztClient/structs/py2pb/convertor.py
AztClient/structs/py2pb/configurator_handles/__init__.py
AztClient/structs/py2pb/configurator_handles/base_handle.py
AztClient/structs/py2pb/configurator_handles/map_handle.py
AztClient/structs/py2pb/configurator_handles/spec_handle.py
AztClient/structs/py2pb/configurators/__init__.py
AztClient/structs/py2pb/configurators/any.py
AztClient/structs/py2pb/configurators/base.py
AztClient/structs/py2pb/configurators/copy.py
AztClient/structs/py2pb/configurators/datetime.py
AztClient/structs/py2pb/configurators/decimal.py
AztClient/structs/py2pb/configurators/map.py
AztClient/structs/py2pb/configurators/multidatetime.py
AztClient/structs/py2pb/configurators/repeat.py
AztClient-1.0.4.dist-info/LICENSE.txt
AztClient-1.0.4.dist-info/METADATA
AztClient-1.0.4.dist-info/WHEEL
AztClient-1.0.4.dist-info/top_level.txt
AztClient-1.0.4.dist-info/RECORD
