Metadata-Version: 2.1
Name: AztClient
Version: 1.0.4
Summary: AztQuant Server Python Client
Author-email: Qujamlee <qujamlee@126.com>
Maintainer-email: Qujamlee <qujamlee@126.com>
License: GNU Lesser General Public License (LGPL)
Project-URL: homepage, https://www.aztquant.com
Project-URL: documentation, https://www.aztquant.com
Project-URL: repository, https://gitee.com/Qujamlee/azt-client.git
Keywords: azt,aztve,aztquant,quant
Classifier: Development Status :: 4 - Beta
Classifier: Intended Audience :: Developers
Classifier: Topic :: Software Development :: Build Tools
Classifier: License :: OSI Approved :: GNU Lesser General Public License v3 or later (LGPLv3+)
Classifier: Programming Language :: Python :: 3.7
Classifier: Programming Language :: Python :: 3.8
Classifier: Programming Language :: Python :: 3.9
Classifier: Programming Language :: Python :: 3.10
Requires-Python: >=3.7
License-File: LICENSE.txt
Requires-Dist: pandas
Requires-Dist: colorlog (>=6.6.0)
Requires-Dist: pyzmq (>=23.2.0)
Requires-Dist: grpcio (>=1.47.0)
Requires-Dist: protobuf (>=3.19.4)
